guanine_crystal_analysis/__init__.py
guanine_crystal_analysis/_sample_data.py
guanine_crystal_analysis/_widget.py
guanine_crystal_analysis/napari.yaml
guanine_crystal_analysis/_tests/__init__.py
guanine_crystal_analysis/_tests/test_sample_data.py
guanine_crystal_analysis/_tests/test_widget.py
guanine_crystal_analysis/cl_classifier/__init__.py
guanine_crystal_analysis/cl_classifier/object_classifier_20220523_intensity.cl
guanine_crystal_analysis/cl_classifier/object_classifier_20220523_shape.cl
guanine_crystal_analysis/cl_classifier/object_classifier_20220523_shape_intensity.cl
guanine_crystal_analysis/cl_classifier/object_classifier_20220523_size.cl
guanine_crystal_analysis/cl_classifier/object_classifier_20220523_size_intensity.cl
guanine_crystal_analysis/cl_classifier/object_classifier_20220523_size_shape.cl
guanine_crystal_analysis/cl_classifier/object_classifier_20220523_size_shape_intensity.cl
guanine_crystal_analysis/cl_segmenter/__init__.py
guanine_crystal_analysis/cl_segmenter/object_segmenter_20220523_sorted.cl
guanine_crystal_analysis-0.0.2.dist-info/LICENSE
guanine_crystal_analysis-0.0.2.dist-info/METADATA
guanine_crystal_analysis-0.0.2.dist-info/WHEEL
guanine_crystal_analysis-0.0.2.dist-info/entry_points.txt
guanine_crystal_analysis-0.0.2.dist-info/top_level.txt
guanine_crystal_analysis-0.0.2.dist-info/RECORD
