Metadata-Version: 2.1
Name: guanine-crystal-analysis
Version: 0.0.2
Summary: A plugin for the guanine crystal segmentation, classification and characterization in the zebrafish eye
Home-page: https://github.com/biapol/guanine-crystal-analysis
Author: Mara Lampert
Author-email: mara_harriet.lampert@mailbox.tu-dresden.de
License: BSD-3-Clause
Project-URL: Bug Tracker, https://github.com/biapol/guanine-crystal-analysis/issues
Project-URL: Documentation, https://github.com/biapol/guanine-crystal-analysis#README.md
Project-URL: Source Code, https://github.com/biapol/guanine-crystal-analysis
Project-URL: User Support, https://github.com/biapol/guanine-crystal-analysis/issues
Classifier: Development Status :: 2 - Pre-Alpha
Classifier: Framework :: napari
Classifier: Intended Audience :: Developers
Classifier: License :: OSI Approved :: BSD License
Classifier: Operating System :: OS Independent
Classifier: Programming Language :: Python
Classifier: Programming Language :: Python :: 3
Classifier: Programming Language :: Python :: 3 :: Only
Classifier: Programming Language :: Python :: 3.8
Classifier: Programming Language :: Python :: 3.9
Classifier: Programming Language :: Python :: 3.10
Classifier: Topic :: Scientific/Engineering :: Image Processing
Requires-Python: >=3.8
License-File: LICENSE
Requires-Dist: numpy
Requires-Dist: magicgui
Requires-Dist: qtpy
Requires-Dist: apoc
Requires-Dist: scikit-image
Requires-Dist: pandas
Requires-Dist: napari-simpleitk-image-processing
Requires-Dist: napari-skimage-regionprops
Requires-Dist: pyclesperanto-prototype
Requires-Dist: scikit-learn
Requires-Dist: napari-workflows
Provides-Extra: testing
Requires-Dist: tox ; extra == 'testing'
Requires-Dist: pytest ; extra == 'testing'
Requires-Dist: pytest-cov ; extra == 'testing'
Requires-Dist: pytest-qt ; extra == 'testing'
Requires-Dist: napari ; extra == 'testing'
Requires-Dist: pyqt5 ; extra == 'testing'
